{"name": "Let's go for some green! And I don't mean money... This is the ultimate park, church, castle tour inside Vienna! (Also in Winter)", "url": "https://www.triip.me/api/v1/triips/13513", "price": 40.0, "cover": "https://triip.imgix.net/triips/images/13513/13640/384e7d12608e11e599bf661e02d2f542_533x400.jpg", "tour_guide": "Alexey", "place": {"country": 70, "slug": "vienna", "id": 479, "name": "Vienna"}, "description": "The Steinhofgr\u00fcnde Park is some kind of \"hidden treasure\" in Vienna, because it is not commonly visited by tourists. Mainly it is the locals who have the luck of knowing about it and can enjoy it's vast variety of trees, colors and landscapes, all of which have a particular beauty in every season."}