{"name": "Saigon Sight Seeing and Foodies Tour", "url": "https://www.triip.me/api/v1/triips/14473", "price": 30.0, "cover": "https://triip.imgix.net/triips/images/14473/14934/b8cdc0a6760f11e588ad560310b3577b_684x684.jpg", "tour_guide": "Lananh", "place": {"country": 1, "slug": "ho-chi-minh", "id": 1, "name": "Ho Chi Minh"}, "description": "I will become your motorbike driver, translator, your friend and your tour guide as well. In my tour, you have chance to visit not only famous destinations in Saigon but also \u00a0can reach out the local life of Saigon people. You can see Saigon in different sides. Beside plenty of sky buildings in the central, you also see many of slumps next to. You will experience South Vietnam cuisine with street food style and coffee which will become your unfogetable memory about Vietnam."}