{"name": "Here and there in Lisbon (A photographic journey )", "url": "https://www.triip.me/api/v1/triips/14586", "price": 30.0, "cover": "https://triip.imgix.net/triips/images/14586/15044/d43058dc781b11e59c2f1ad9a1dcb4ed_1024x768.jpg", "tour_guide": "vasco", "place": {"country": 29, "slug": "lisbon", "id": 531, "name": "Lisbon"}, "description": "Lisbon is a very special city with a wonderful light, history and natural beauty. By taking this trip,you will have the chance to discover the best places,views and angles to get your best shoot. Bring home your fantastic photographic memories. Its quite an experience to walk from downtown,throught crowded large streets,to narrow alleys until you reach the Moorish castle on the top."}