{"name": "Sydney. Half day. option2", "url": "https://www.triip.me/api/v1/triips/15579", "price": null, "cover": "https://triip.imgix.net/triips/images/15579/16221/1d28e9b68a8a11e5b1bdb2fc057ddac1_356x125.jpg", "tour_guide": "Victoria", "place": {"country": 36, "slug": "sydney", "id": 218, "name": "Sydney"}, "description": "This walk start from Circular Quay and cover the\u00a0big part\u00a0of historical\u00a0attractions \u00a0of Sydney. We visit the Rocks\u00a0which established shortly after the colony's formation in 1788. Iconic Opera House! Royal Botanic Garden and few other historical places. We finish our walk in one of the best Chinese Restaurants of Sydney Din Tai Fung."}