{"name": "Hanoi Cooking Class with local people", "url": "https://www.triip.me/api/v1/triips/15857", "price": 55.0, "cover": "https://triip.imgix.net/triips/images/15857/16516/9aeb4fe49c8a11e5883f328f60e55842_800x601.jpg", "tour_guide": "Sunny", "place": {"country": 1, "slug": "hanoi", "id": 6, "name": "Hanoi"}, "description": "Get away from\nthe classical cooking classes and learn the Vietnamese cuisine at a local home.\nWe will start our day with a short stop at a local market. Here you will browse\nhundreds of stalls, and interact with vendors selling everything from garlic to\ntapioca flour. Take in all the colors, sights and smells! Hanoi\u2019s markets are\nworld famous, and you\u2019ll quickly see why."}