{"name": "Mekong Delta and Phu Quoc island family vacation", "url": "https://www.triip.me/api/v1/triips/16261", "price": null, "cover": "https://triip.imgix.net/triips/images/16261/17009/075780aabf1b11e59162de9b143fd045_1024x685.jpg", "tour_guide": "Intimate Asia", "place": {"country": 1, "slug": "phu-quoc", "id": 22, "name": "Phu Quoc"}, "description": "This trip takes your family to the mighty Mekong river,\ngives you a real insight and understanding into how life is lived along the\nbanks and in the Vietnam Delta region. Enjoy authentic cruise on Le Cochinchine\ncruise while discovering floating markets, pagodas and local villages. Finally,\nenjoy your family holiday on beautiful beach of Phu Quoc Island."}