{"name": "Your Personal Photographer", "url": "https://www.triip.me/api/v1/triips/17279", "price": null, "cover": "https://triip.imgix.net/triips/images/17279/18221/529d61b2007d11e6860d069b59697fe8_5472x3648.jpg", "tour_guide": "Gideon", "place": {"country": 48, "slug": "toronto", "id": 560, "name": "Toronto"}, "description": "Have you ever wanted amazing pictures of your special trip, but all you have is your smart phone? I have the perfect solution. Whatever you want to do, it's your day. Whether it's eating dumplings china town, the Toronto Aquarium, going to the top of the CN tower or going to check out some local music. You can plan the whole trip and I will just be fly on the wall or I can make recommendations and show you some of my favourite Toronto secrets."}