{"name": "EXPLORE PHONG NHA IN 4,5KM DEPTH - 1 DAY TOUR", "url": "https://www.triip.me/api/v1/triips/17876", "price": 94.0, "cover": "https://triip.imgix.net/triips/images/17876/18866/f322e1b6546011e686a89e65d88d2787_550x366.jpg", "tour_guide": "Sondoong", "place": {"country": 1, "slug": "quang-binh", "id": 56, "name": "Quang Binh"}, "description": "You will become professional adventurers to explore the mysterious underground river and impressive beauty of Phong Nha cave with kayak, dragon boat or piragua, flashlights and other specialized equipment.A new experience on the longest underground river in the world will provide you with an unforgettable experience. Joining this unique tour, you will be felt and experienced full 7 outstanding global criteria of Phong Nha cave."}