{"name": "Type-A-Retreat - World's First retreat for start up CEOs and Founders - Angel Round", "url": "https://www.triip.me/api/v1/triips/20135", "price": 2499.0, "cover": "https://triip.imgix.net/triips/images/20135/21564/1bc21eacc67111e686bb8261a4f67bdc_4928x3264.JPG", "tour_guide": "Type-A Retreat", "place": {"country": 41, "slug": "western-bhutan", "id": 308, "name": "Western Bhutan"}, "description": "You are doing an awesome job to make change for the better world through your startup. Heroic, actually."}