{"name": "3 countries", "url": "https://www.triip.me/api/v1/triips/21413", "price": null, "cover": "https://triip.imgix.net/triips/images/21413/23196/2f9ce04833d011e795678ec3985d5ce8_4032x3024.JPG", "tour_guide": "xavier", "place": {"country": 81, "slug": "luxembourg", "id": 535, "name": "Luxembourg"}, "description": "This tour will give you a feel for how irrelevant\u00a0borders are in this part of the world as we will spend a whole day moving between\u00a0Luxembourg, France and Germany and spend quality time at each stop."}