{"name": "Everest Experience: Mountain Flight Tour", "url": "https://www.triip.me/api/v1/triips/2247", "price": 280.0, "cover": "https://triip.imgix.net/triips/images/2247/2371/7ef39ec8737711e485e716c1c5b7ae1e.jpg", "tour_guide": "Ram", "place": {"country": 37, "slug": "kathmandu", "id": 185, "name": "Kathmandu"}, "description": "Highlights:\n\n\uf06c Life time experiencing to See top of the world's Mount Everest\n\uf06c Enjoy breath-taking views of this iconic mountain\n\uf06c Marvel at several other Himalayan peaks"}