{"name": "Cooking Class At Tra Que Village", "url": "https://www.triip.me/api/v1/triips/2510", "price": null, "cover": "https://triip.imgix.net/triips/images/2510/2640/475cda5c8cad11e4a719869cf662b217.jpg", "tour_guide": "Hoi An Travel", "place": {"country": 1, "slug": "hoi-an", "id": 15, "name": "Hoi An"}, "description": "Tra Que village is famous for very fresh vegetables and vietnamese herbs.Most of tropical vegetables cam grow well at Tra Que and their flavor and taste are so distinctive that they can never be mistaken for products of the same kind from other loacalities.You will have a chance to learn how to make tasty traditional dishes from vegetable."}