{"name": "Rothenburg And The Romantic Road", "url": "https://www.triip.me/api/v1/triips/5073", "price": null, "cover": "https://triip.imgix.net/triips/images/5073/5246/2ca3643ed23e11e49b18f6765a13f662.jpg", "tour_guide": "Bavarian Day Tours", "place": {"country": 47, "slug": "munich", "id": 325, "name": "Munich"}, "description": "Rothenburg \u2026 the famous walled city, frozen in time \u2026 it is every bit as worth it as you have always heard!  Let us take you to Rothenburg for the day and transport you into the world of the middle ages."}