{"name": "One Day Tour To Machu Picchu", "url": "https://www.triip.me/api/v1/triips/5098", "price": 275.0, "cover": "https://triip.imgix.net/triips/images/5098/5271/5bf47634d29211e485794a22b6ff1a14.jpg", "tour_guide": "Incatrekkers", "place": {"country": 25, "slug": "machu-picchu", "id": 213, "name": "Machu Picchu"}, "description": "This tour starts with unforgettable train journey. It`s a good tour for those who do not have much time in Cusco and want to enjoy the beauty of the citadel of Machu Picchu. Along the way we will enjoy a breathtaking scenery, surrounding mountains and local villages."}