{"name": "Montserrat And Cava Tour", "url": "https://www.triip.me/api/v1/triips/5787", "price": 925.0, "cover": "https://triip.imgix.net/triips/images/5787/5964/c734faaad9e911e4adaddef115732dc2.jpg", "tour_guide": "City Tours Barcelona ", "place": {"country": 46, "slug": "barcelona", "id": 317, "name": "Barcelona"}, "description": "VISIT THE MONTSERRAT MOUNTAIN AND TASTE THE CATALAN CAVA\n\nThe Montserrat and Cava Tour from Barcelona combines a visit to the beautiful Montserrat mountain in west Barcelona and the Freixenet Company, the biggest producer of champagne (in Spanish: Cava) in the world.\n\nOver the years Montserrat has been the goal not only for thousands of pilgrims, but also for architects like Antoni Gaud\u00ed and Jean Nouvel, who have been inspired by the unique forms of the rocks and by the beautiful natural park on the mountain."}