{"name": "Montserrat And Winery Tour", "url": "https://www.triip.me/api/v1/triips/5897", "price": 87.0, "cover": "https://triip.imgix.net/triips/images/5897/6075/9af2ed8cdcd511e49d3aee6d2a3454ab.jpg", "tour_guide": "Explore Catalunya", "place": {"country": 46, "slug": "barcelona", "id": 317, "name": "Barcelona"}, "description": "Capture the heart of Catalunya on this day tour to the iconic Montserrat and it's Royal Basilica and enjoy some sparkle in the rural cava cellars of world famous cava producer, Codorniu.\n\nThe day starts with a morning visit to Montserrat where you\u2019ll explore the monastic centre of Catalonia, home to the famous black virgin & la Escolania (children\u2019s boy choir). You\u2019ll also have time to explore the magnificent natural park & mountains with spectacular views over the plains of Catalonia.\n\nAfter lunch, you\u2019ll be transported through the back roads to the wine country, where you\u2019ll visit the renowned local winery, Codorniu for a tour in their vast underground cellars followed by a tasting of the famous Cava 'champagne'."}