{"name": "Tulum Zip Line Combo Tour", "url": "https://www.triip.me/api/v1/triips/6317", "price": 125.0, "cover": "https://triip.imgix.net/triips/images/6317/6502/ee49c806e24411e4a43416b197d8c92d.jpg", "tour_guide": "Playa del Carmen Tours", "place": {"country": 24, "slug": "playa-del-carmen", "id": 343, "name": "Playa del Carmen "}, "description": "One of the most popular tours in Playa del Carmen just got better!  Now not only can you enjoy the exciting and enlightening Jungle Maya Expedition, but you can enjoy the mystery and dazzling clifftop setting of the Tulum Mayan Ruins site as well.\n\nTulum is the second most visited Mayan Ruins site in the Riviera Maya, behind only Chichen Itza.  Aside from being the only walled city in the Mayan Empire, Tulum is unique for it's awesome clifftop location, overlooking the azure waters of the Caribbean Sea and the 4th best beach in the world, according to National Geographic."}