{"name": "Monkey Tour", "url": "https://www.triip.me/api/v1/triips/6443", "price": 70.0, "cover": "https://triip.imgix.net/triips/images/6443/6628/6c198da8e30711e4af56cedeea45c762.jpg", "tour_guide": "Encounters", "place": {"country": 24, "slug": "playa-del-carmen", "id": 343, "name": "Playa del Carmen "}, "description": "Walking around in this 100% natural habitat you have the chance to encounter groups of the resident Central American Spider Monkeys. It is an easy walk, including some viewpoints from where you can easily get to know the different coastal habitats of the Mayan Riviera."}