{"name": "The Original Downtown Vallarta Tour", "url": "https://www.triip.me/api/v1/triips/6485", "price": 49.0, "cover": "https://triip.imgix.net/triips/images/6485/6670/ece5255ce32311e4922ccedeea45c762.jpg", "tour_guide": "Vallarta Food Tours", "place": {"country": 24, "slug": "puerto-vallarta", "id": 354, "name": "Puerto Vallarta "}, "description": "One-of-a-kind Food Tastings \u2013 A guided 3-3/12 hours food and city walking tour featuring 10 food tasting locations carefully chosen to highlight the best regional flavors Puerto Vallarta has to offer. Enough for a satisfying lunch, you will enjoy a sampling of mouth-watering food at family-owned restaurants and stands, sip on refreshing local drinks and even enjoy a fresh tortilla straight out of the conveyer belt. Learn about food from the colorful local folks whose pride in their craft is only matched by the effusiveness of their spirit. Stops include Vallarta\u2019s best mole enchiladas, traditional ceviche tostadas, tortilla factory, fresh coconut, tacos from an authentic taco stand, traditional drinks, savory soups, regional candies and more. All food tastings are included in the ticket price. See all Tasting Locations to the right."}