{"name": "El Chimo Scuba Diving", "url": "https://www.triip.me/api/v1/triips/6755", "price": 135.0, "cover": "https://triip.imgix.net/triips/images/6755/6954/5ede9582e70011e4ac38baf32b6e02d3_2896x1944.jpg", "tour_guide": "Amigo Tours Vallarta", "place": {"country": 24, "slug": "puerto-vallarta", "id": 354, "name": "Puerto Vallarta "}, "description": "El Chimo Scuba Diving is a fishing village situated twenty five miles south of the bay. El Chimo is known for their depth depths and fierce currents. You can dive depths of 70 feet all the way to100 feet, and must be advanced diver to book this scuba diving tour. You may also choose this location for your second day advanced training."}